cayenneLPP/__init__.py
cayenneLPP/cayenneLPP.py
cayenneLPP-0.5b3.dist-info/DESCRIPTION.rst
cayenneLPP-0.5b3.dist-info/METADATA
cayenneLPP-0.5b3.dist-info/RECORD
cayenneLPP-0.5b3.dist-info/WHEEL
cayenneLPP-0.5b3.dist-info/metadata.json
cayenneLPP-0.5b3.dist-info/top_level.txt
