Metadata-Version: 2.0
Name: cayenneLPP
Version: 0.5b3
Summary: A module for the Cayenne Low Power Packet format
Home-page: https://github.com/jojo-/py-cayenne-lpp
Author: Johan Barthelemy
Author-email: johan@uow.edu.au
License: MIT
Keywords: Cayenne,Low Power Payload,LPP
Platform: UNKNOWN
Classifier: Development Status :: 4 - Beta
Classifier: Intended Audience :: Developers
Classifier: License :: OSI Approved :: MIT License
Classifier: Programming Language :: Python :: 2
Classifier: Programming Language :: Python :: 3
Classifier: Programming Language :: Python :: Implementation :: MicroPython
